{
    "key": "group_61f18711e0f85",
    "title": "Sidebar Hours",
    "fields": [
        {
            "key": "field_61f1873070508",
            "label": "Venue",
            "name": "items",
            "type": "repeater",
            "instructions": "",
            "required": 0,
            "conditional_logic": 0,
            "wrapper": {
                "width": "",
                "class": "",
                "id": ""
            },
            "acfe_repeater_stylised_button": 0,
            "collapsed": "",
            "min": 1,
            "max": 0,
            "layout": "table",
            "button_label": "Add Venue",
            "sub_fields": [
                {
                    "key": "field_61f1877070509",
                    "label": "Venue Name",
                    "name": "title",
                    "type": "text",
                    "instructions": "ex. \"Palmer Florida\"",
                    "required": 1,
                    "conditional_logic": 0,
                    "wrapper": {
                        "width": "25",
                        "class": "",
                        "id": ""
                    },
                    "default_value": "",
                    "placeholder": "",
                    "prepend": "",
                    "append": "",
                    "maxlength": ""
                },
                {
                    "key": "field_61f1879d7050a",
                    "label": "Venue Hours",
                    "name": "hours",
                    "type": "text",
                    "instructions": "ex. \"7:30AM - 5PM\"",
                    "required": 1,
                    "conditional_logic": 0,
                    "wrapper": {
                        "width": "25",
                        "class": "",
                        "id": ""
                    },
                    "default_value": "",
                    "placeholder": "",
                    "prepend": "",
                    "append": "",
                    "maxlength": ""
                }
            ]
        }
    ],
    "location": [
        [
            {
                "param": "page_type",
                "operator": "==",
                "value": "front_page"
            },
            {
                "param": "page_type",
                "operator": "!=",
                "value": "front_page"
            }
        ]
    ],
    "menu_order": 0,
    "position": "normal",
    "style": "default",
    "label_placement": "left",
    "instruction_placement": "label",
    "hide_on_screen": "",
    "active": true,
    "description": "",
    "show_in_rest": 0,
    "acfe_display_title": "",
    "acfe_autosync": [
        "json"
    ],
    "acfe_form": 0,
    "acfe_meta": "",
    "acfe_note": "",
    "modified": 1643218900
}